{
  "index": 1239,
  "fromLine": "From contact@mailer.humblebundle.com Sat Oct 11 22:22:38 2025",
  "subject": "Automate your world with help from Mammoth Club",
  "from": "\"Humble Bundle\" <contact@mailer.humblebundle.com>",
  "to": "liencf@gmail.com",
  "date": "2025-10-11T22:22:37.000Z",
  "messageId": "<20251011222237.b3194c8da6c47141@mailer.humblebundle.com>",
  "topContentType": "[object Object]",
  "mime": {
    "hasText": true,
    "hasHtml": true,
    "attachmentCount": 0
  },
  "headers": {
    "delivered-to": [
      {
        "address": "liencf@gmail.com",
        "name": ""
      }
    ],
    "received": "by 2002:a05:7010:df93:b0:4ca:2b22:f54c with SMTP id ok19csp3138482mdb; Sat, 11 Oct 2025 15:22:38 -0700 (PDT),from d149.c153.cordialmail.net (d149.c153.cordialmail.net. [192.112.153.149]) by mx.google.com with UTF8SMTPS id d2e1a72fcca58-7992b0676f7si3926611b3a.172.2025.10.11.15.22.37 for <liencf@gmail.com> (version=TLS1_2 cipher=ECDHE-ECDSA-AES128-GCM-SHA256 bits=128/128); Sat, 11 Oct 2025 15:22:38 -0700 (PDT),by 0a98ac02ca92ce29800da69148818995ba607ea464c4d2f8bcee0c31c53b6da4 with HTTP id 68ead8adb8bc287729e51b63; Sat, 11 Oct 2025 22:22:37 GMT",
    "x-google-smtp-source": "AGHT+IGp6dayvQxzPsBBn01/+jRS2RtgoCYdjDVTN10yKSaVV3bVuwWojTOVuPIYvk2I25xaMc4v",
    "x-received": "by 2002:a05:6a21:3386:b0:2fb:add5:5570 with SMTP id adf61e73a8af0-32da83e2477mr22861927637.33.1760221358553; Sat, 11 Oct 2025 15:22:38 -0700 (PDT)",
    "arc-seal": "i=1; a=rsa-sha256; t=1760221358; cv=none; d=google.com; s=arc-20240605; b=bTRWpXBKxfbxJpJ9rq1FscedBeb9mAM1lz4pdotDjcGzHLKgYlOo2fmTRrftG9xf1N ohn6xnRo9C3qOte0EiRJ+KCezPYllqaxoh8Ea28TbbDjePjtnnriQxigPYHCWPJJ1PgI L+LvPupr8wdxfmuwnvc8TKHrgimUaKDZWgBkKWAsE2EVE4cL89yqR6l5z5rBEhv2SiMH 5pO+zOIS53waLYWb2+k0z/rds9SBIplZmKG4XEQ4Uq7Dkj7ci004lt/19A77Mnt7ujFu H0vTqqJCiGIDNBmzl36qDpSJ1QRB/4eRcuu9z1jGF9vP4xWSpQfgVrIU3xRPIzUONM6e hKlA==",
    "arc-message-signature": "i=1; a=rsa-sha256; c=relaxed/relaxed; d=google.com; s=arc-20240605; h=content-transfer-encoding:message-id:reply-to:bimi-selector:to:from :subject:mime-version:date:sender:list-unsubscribe :list-unsubscribe-post:dkim-signature:dkim-signature; bh=Nvw/EDp1R/eCmYnJDUmKsGZ90deQG+EoLDpXDuJGHyk=; fh=hnWLqYXx/enUl3blN9H38oqkLIXAr0tyRzvlFpRYzeI=; b=JXExSbGdZB/zUMP/Rd0vSaPvBFPfco5xtQTHTzcAWYCBWUTX/d9HTLcXNq1K09PnLo Ebq8rZaXipp7iDI8426rH8y2VGaLgzCk+pk5ULBPzvJZHSq2cKr73H9rmRCfPhSBGeUC aqGnMxYeugvFjBbHNQ4UswYySb+5n9kpSmgAPDowdK+YcDU0mDl5tE1uCjrkn9kH6lmh Z1qgOxO7CPzDP0sYIH6cxo/HsEZtKTK/2siekYKfB3y3oIrKl/Jq7LN0rSYuVsKa37Al hWyX6KSQBooV6eeNm02n30BU3hXvMWz8SPGJ+98r42x7q9VztZJumQGZW7VM2xMGax+l tkNA==; dara=google.com",
    "arc-authentication-results": "i=1; mx.google.com; dkim=pass header.i=@mailer.humblebundle.com header.s=crdl01 header.b=KUppVXl9; dkim=pass header.i=@mailgun.org header.s=mg header.b=FE9DJAHI; spf=pass (google.com: domain of bounce+e250bd.460f1c-liencf=gmail.com@mailer.humblebundle.com designates 192.112.153.149 as permitted sender) smtp.mailfrom=\"bounce+e250bd.460f1c-liencf=gmail.com@mailer.humblebundle.com\"; dmarc=pass (p=QUARANTINE sp=QUARANTINE dis=NONE) header.from=humblebundle.com",
    "return-path": [
      {
        "address": "bounce+e250bd.460f1c-liencf=gmail.com@mailer.humblebundle.com",
        "name": ""
      }
    ],
    "received-spf": "pass (google.com: domain of bounce+e250bd.460f1c-liencf=gmail.com@mailer.humblebundle.com designates 192.112.153.149 as permitted sender) client-ip=192.112.153.149;",
    "authentication-results": "mx.google.com; dkim=pass header.i=@mailer.humblebundle.com header.s=crdl01 header.b=KUppVXl9; dkim=pass header.i=@mailgun.org header.s=mg header.b=FE9DJAHI; spf=pass (google.com: domain of bounce+e250bd.460f1c-liencf=gmail.com@mailer.humblebundle.com designates 192.112.153.149 as permitted sender) smtp.mailfrom=\"bounce+e250bd.460f1c-liencf=gmail.com@mailer.humblebundle.com\"; dmarc=pass (p=QUARANTINE sp=QUARANTINE dis=NONE) header.from=humblebundle.com",
    "dkim-signature": "[object Object],[object Object]",
    "x-mailgun-sid": "WyI5MzA1MiIsImxpZW5jZkBnbWFpbC5jb20iLCI0NjBmMWMiXQ==",
    "list": "[object Object]",
    "x-feedback-id": "contact@mailer.humblebundle.com:msID:102:68e94bcd473068c0af0ef01b:ot:66f4b28391616c98ca622260:mailgun,102:102_68e94bcd473068c0af0ef01b_ot:5fa2077a730d25f072bfb2e3:cordial",
    "x-mailgun-sending-ip-pool-name": "hb-d",
    "x-mailgun-sending-ip-pool": "66f46832e4fa9b2444147fb3",
    "x-mailgun-sending-ip": "192.112.153.149",
    "sender": [
      {
        "address": "contact@mailer.humblebundle.com",
        "name": ""
      }
    ],
    "date": "Sun Oct 12 2025 06:22:37 GMT+0800 (台北標準時間)",
    "mime-version": "1.0",
    "subject": "Automate your world with help from Mammoth Club",
    "from": [
      {
        "address": "contact@mailer.humblebundle.com",
        "name": "Humble Bundle"
      }
    ],
    "to": [
      {
        "address": "liencf@gmail.com",
        "name": ""
      }
    ],
    "x-mailgun-tag": "msID:102:68e94bcd473068c0af0ef01b:ot",
    "x-mailgun-track-opens": "true",
    "bimi-selector": "v=BIMI1; s=default;",
    "x-crdl-mc": "102:68e94bcd473068c0af0ef01b:ot:5fa2077a730d25f072bfb2e3:1",
    "reply-to": [
      {
        "address": "contact@humblebundle.com",
        "name": ""
      }
    ],
    "x-mailgun-variables": "{\"crdlEnv\": \"production\", \"mcID\": \"102:68e94bcd473068c0af0ef01b:ot:5fa2077a730d25f072bfb2e3:1\"}",
    "message-id": "<20251011222237.b3194c8da6c47141@mailer.humblebundle.com>",
    "content-type": "text/html",
    "content-transfer-encoding": "quoted-printable"
  },
  "attachments": []
}