{
  "index": 252,
  "fromLine": "From updates-noreply@linkedin.com Mon Nov 10 13:02:14 2025",
  "subject": "大大帶我飛 Dadafly Founder recently posted",
  "from": "\"LinkedIn\" <updates-noreply@linkedin.com>",
  "to": "\"Alex Lien\" <liencf@gmail.com>",
  "date": "2025-11-10T13:02:00.000Z",
  "messageId": "<976529691.26874319.1762779720831@lor1-app45185.prod.linkedin.com>",
  "topContentType": "[object Object]",
  "mime": {
    "hasText": true,
    "hasHtml": true,
    "attachmentCount": 0
  },
  "headers": {
    "delivered-to": [
      {
        "address": "liencf@gmail.com",
        "name": ""
      }
    ],
    "received": "by 2002:a05:7011:1e11:b0:4ec:1446:8385 with SMTP id uy17csp1147153mdb; Mon, 10 Nov 2025 05:02:15 -0800 (PST),from maile-da.linkedin.com (maile-da.linkedin.com. [108.174.6.201]) by mx.google.com with ESMTPS id 41be03b00d2f7-ba8f5794514si7455970a12.231.2025.11.10.05.02.13 for <liencf@gmail.com> (version=TLS1_3 cipher=TLS_AES_256_GCM_SHA384 bits=256/256); Mon, 10 Nov 2025 05:02:14 -0800 (PST)",
    "x-google-smtp-source": "AGHT+IHJM3qm76f0MxqWAUDbFgIqAoxJ1tmjZXPakqEedTsoH0BCtWxu4UuE6TpGTWTkp0QSy83i",
    "x-received": "by 2002:a05:6a20:9e47:b0:2d7:1689:e3bb with SMTP id adf61e73a8af0-352b8385cb4mr13136210637.22.1762779734401; Mon, 10 Nov 2025 05:02:14 -0800 (PST)",
    "arc-seal": "i=1; a=rsa-sha256; t=1762779734; cv=none; d=google.com; s=arc-20240605; b=hSXsQD6YnLj073jK932AR1Ye4lqlv+JodkEdRNF6sOp0WgiNV8WVzvLhNCAJ6TWq2y SKdWb/AINEupkEcOOPobdrY/HVI8bQcRl9V+lRd3d7GQbZyaEaI92+YQU5sfHvVDQ4ea Rzl0IuDstZKJuXBmd6Qldr9ko2ZDxZ1uA7NdIzyaeGGDKT/71KKjZg6go+lgMJLK0gug T3eD7pOKFWrOuHc46Nl2YhwoXWzStDWKH/IW/64+KfmqPYYb1eLPWgyDwXkMkEut3yX7 TxGekgurvaWMtFd5p8z5WLWIqct6mQcBRSaCgC06KtoFMvcTl2kkED2YoakI+/KgNkyR 5umw==",
    "arc-message-signature": "i=1; a=rsa-sha256; c=relaxed/relaxed; d=google.com; s=arc-20240605; h=require-recipient-valid-since:feedback-id:list-unsubscribe-post :list-unsubscribe:date:to:mime-version:subject:message-id:from :dkim-signature:dkim-signature; bh=TaXS6xQNi8YjCy/4YlvflkVES/LtQxSmaAwk/bF8e4s=; fh=7JPwxgX6qxpLaqNh6wKbtiScFCNZB+DBejc+aAjCBWw=; b=lyyiZpmvlFICdfk8Tz/QmHFp1Q4SUsX+UkfDX022nfC36HQrsEz1aIXXxwAtTqEJei 2n6NKS0+O7r11j6LhaHu59aBzG0UPBFHqLv9ahEl2DsMqV4PCutiw4kV2HST7/C/cKw/ naOVguycM8lR+FoZK7knPOo6CmtB5BG/sJ0tZbhSNBYt5hFvQn5pDkIanJNG9Erqbc/3 jQMJYPpndSJU8dyrMC6VJiNBhF6iH6HVncQbWfq3Y4Hn5ASEyNFyzyvbnsAMj/50w3DN utH4geDbgfIP2vhm9glEdi+pAEFj3OaDtxu07rm7QnXyZnMZhjfJEcVYCLRnoqjql905 N8kQ==; dara=google.com",
    "arc-authentication-results": "i=1; mx.google.com; dkim=pass header.i=@maile.linkedin.com header.s=d2048-202308-0e header.b=t6TQczyo; dkim=pass header.i=@linkedin.com header.s=d2048-202308-00 header.b=lYgKuWnz; spf=pass (google.com: domain of m-qzn06j060ynb5t4fgofkkfxyob4i6qz9xn6dq1ds1zy6ku5xiu9dv1@bounce.linkedin.com designates 108.174.6.201 as permitted sender) smtp.mailfrom=m-qzn06j060ynb5t4fgofkkfxyob4i6qz9xn6dq1ds1zy6ku5xiu9dv1@bounce.linkedin.com; dmarc=pass (p=REJECT sp=REJECT dis=NONE) header.from=linkedin.com",
    "return-path": [
      {
        "address": "m-qzn06j060ynb5t4fgofkkfxyob4i6qz9xn6dq1ds1zy6ku5xiu9dv1@bounce.linkedin.com",
        "name": ""
      }
    ],
    "received-spf": "pass (google.com: domain of m-qzn06j060ynb5t4fgofkkfxyob4i6qz9xn6dq1ds1zy6ku5xiu9dv1@bounce.linkedin.com designates 108.174.6.201 as permitted sender) client-ip=108.174.6.201;",
    "authentication-results": "mx.google.com; dkim=pass header.i=@maile.linkedin.com header.s=d2048-202308-0e header.b=t6TQczyo; dkim=pass header.i=@linkedin.com header.s=d2048-202308-00 header.b=lYgKuWnz; spf=pass (google.com: domain of m-qzn06j060ynb5t4fgofkkfxyob4i6qz9xn6dq1ds1zy6ku5xiu9dv1@bounce.linkedin.com designates 108.174.6.201 as permitted sender) smtp.mailfrom=m-qzn06j060ynb5t4fgofkkfxyob4i6qz9xn6dq1ds1zy6ku5xiu9dv1@bounce.linkedin.com; dmarc=pass (p=REJECT sp=REJECT dis=NONE) header.from=linkedin.com",
    "dkim-signature": "[object Object],[object Object]",
    "from": [
      {
        "address": "updates-noreply@linkedin.com",
        "name": "LinkedIn"
      }
    ],
    "message-id": "<976529691.26874319.1762779720831@lor1-app45185.prod.linkedin.com>",
    "subject": "大大帶我飛 Dadafly Founder recently posted",
    "mime-version": "1.0",
    "content-type": "multipart/alternative",
    "to": [
      {
        "address": "liencf@gmail.com",
        "name": "Alex Lien"
      }
    ],
    "date": "Mon Nov 10 2025 21:02:00 GMT+0800 (台北標準時間)",
    "x-linkedin-class": "EMAIL-DEFAULT",
    "x-linkedin-template": "email_network_conversations_01",
    "x-linkedin-fbl": "m2-aszx7ts4a8fz8upkcnvjpul8k2uj1yfcv93ftmu4wr6s0ruqfrvr0gjhyr5n4jm2envkt95prpn62y0dtf8i5upmyjbfdtyx5wn0hc",
    "x-linkedin-id": "4mpm2t-mht5hu8j-dm",
    "list": "[object Object]",
    "feedback-id": "email_network_conversations_01:linkedin",
    "require-recipient-valid-since": "liencf@gmail.com; Thu, 15 Aug 2013 03:39:15 +0000"
  },
  "attachments": []
}