{
  "index": 321,
  "fromLine": "From cs@autopass.xyz Sat Nov 08 04:17:23 2025",
  "subject": "Autopass 快速通：您的路邊停車訂單收據 (扣款日：2025.11.08)",
  "from": "\"Autopass 快速通客服團隊\" <cs@autopass.xyz>",
  "to": "liencf@gmail.com",
  "date": "2025-11-08T04:17:22.000Z",
  "messageId": "<690ec4521a219_1221aa0802e5@deployment-sidekiq-79b7d5fdf4-fxsmj.mail>",
  "topContentType": "[object Object]",
  "mime": {
    "hasText": true,
    "hasHtml": true,
    "attachmentCount": 0
  },
  "headers": {
    "delivered-to": [
      {
        "address": "liencf@gmail.com",
        "name": ""
      }
    ],
    "received": "by 2002:a05:7010:d801:b0:4d4:9739:2b92 with SMTP id of1csp2344041mdb; Fri, 7 Nov 2025 20:17:24 -0800 (PST),from mailgun.autopass.xyz (mailgun.autopass.xyz. [198.244.55.183]) by mx.google.com with UTF8SMTPS id d2e1a72fcca58-7b0cca5b280si2790913b3a.564.2025.11.07.20.17.23 for <liencf@gmail.com> (version=TLS1_2 cipher=ECDHE-ECDSA-AES128-GCM-SHA256 bits=128/128); Fri, 07 Nov 2025 20:17:23 -0800 (PST),from autopass.xyz (102.195.194.35.bc.googleusercontent.com [35.194.195.102]) by d28a65bb620dba882bafd2747f63fabb118e7ed78db908fd408bed185a9a1507 with SMTP id 690ec4531ce1d6957294c07c (version=TLS1.3, cipher=TLS_AES_128_GCM_SHA256); Sat, 08 Nov 2025 04:17:23 GMT",
    "x-google-smtp-source": "AGHT+IFTrDYN2HoC2zXZUBSScfj/PRHpEQx6SFYhgAw4v4I5jrx7KFqk2ICAHUGEiywWTsEZgSTZ",
    "x-received": "by 2002:a17:903:1a27:b0:297:ec1a:9db8 with SMTP id d9443c01a7336-297ec1a9e0dmr7032895ad.49.1762575443834; Fri, 07 Nov 2025 20:17:23 -0800 (PST)",
    "arc-seal": "i=1; a=rsa-sha256; t=1762575443; cv=none; d=google.com; s=arc-20240605; b=Yi8YIzafFGfNgdp1Q0j2fkKuOr2uwJFHttDiRaevjQFx4YgEtGTNtalYGhpRqBIJKP FPyqmD/4SXUdLi0A59nir8r7L5fwFtU+RUi98T7mD7k4vPqTvor/FISwfO0cza6SoBy7 ZovT8T4nDbtgN0aaP5jJqyc7UbWgSaHL46HMKRKbP48BMUQQYInfHrTbF1zuwSA1xk6U pEWkIy3EFd6Q2gwsttEaEMFKEEiWuP7Wb+08Doy1cDbxoX2a1gIkGD/tbq6lSwSKOaat 3kdLkb1C/cB/WEtMlnxrsiH8rUKY+xGGWYZxCMtdj0qvr/rST7QUDX8qHoiFtJtR9dY5 N05g==",
    "arc-message-signature": "i=1; a=rsa-sha256; c=relaxed/relaxed; d=google.com; s=arc-20240605; h=content-transfer-encoding:mime-version:subject:message-id:to:from :date:sender:dkim-signature:dkim-signature; bh=mEPeQ8JSKVNH55T4ymiAuDi4SyYeif5vl+dyrp2NZqY=; fh=hnWLqYXx/enUl3blN9H38oqkLIXAr0tyRzvlFpRYzeI=; b=X9hyXLmjaMk9Qo+TtZZq7w71p3ru92HuNvPIhSFyfGrJymYNwWLA4MUuJlrf9JhXFi j4IRuCEP38rmNtAV3TqoDTAcNWk51cuHY7x3Z+jFejhF6qjx89kvR6K9FbiYENxdla6i 8LC7qFu40yhA8EFeHfKE+h7nWNqeZYwG9e2LzifvPkbADmaBhFHBAS+A3cuFYy4b7AVp e2gcdxRoaAOap+XUILiL3GyCgHvYzwAYQVOETOu764Sy/vk0nSCOmRaEGJzWK+60biuY 8oVNl0sZffcZChA8wCMQwLkzF27dwNXSpM3SlRPHbxEll/DNUBbK3XGQxgxK3mGpFLFX Cs/w==; dara=google.com",
    "arc-authentication-results": "i=1; mx.google.com; dkim=pass header.i=@autopass.xyz header.s=mailo header.b=E3wLZKRi; dkim=pass header.i=@mailgun.org header.s=mg header.b=L1Rt883p; spf=pass (google.com: domain of bounce+a80ca7.5d2093-liencf=gmail.com@autopass.xyz designates 198.244.55.183 as permitted sender) smtp.mailfrom=\"bounce+a80ca7.5d2093-liencf=gmail.com@autopass.xyz\"; dmarc=pass (p=QUARANTINE sp=QUARANTINE dis=NONE) header.from=autopass.xyz",
    "return-path": [
      {
        "address": "bounce+a80ca7.5d2093-liencf=gmail.com@autopass.xyz",
        "name": ""
      }
    ],
    "received-spf": "pass (google.com: domain of bounce+a80ca7.5d2093-liencf=gmail.com@autopass.xyz designates 198.244.55.183 as permitted sender) client-ip=198.244.55.183;",
    "authentication-results": "mx.google.com; dkim=pass header.i=@autopass.xyz header.s=mailo header.b=E3wLZKRi; dkim=pass header.i=@mailgun.org header.s=mg header.b=L1Rt883p; spf=pass (google.com: domain of bounce+a80ca7.5d2093-liencf=gmail.com@autopass.xyz designates 198.244.55.183 as permitted sender) smtp.mailfrom=\"bounce+a80ca7.5d2093-liencf=gmail.com@autopass.xyz\"; dmarc=pass (p=QUARANTINE sp=QUARANTINE dis=NONE) header.from=autopass.xyz",
    "dkim-signature": "[object Object],[object Object]",
    "x-mailgun-sid": "WyJkNDI0MSIsImxpZW5jZkBnbWFpbC5jb20iLCI1ZDIwOTMiXQ==",
    "x-feedback-id": "cs@autopass.xyz::5fc89637e17f268cb902e4c2:mailgun",
    "x-mailgun-sending-ip": "198.244.55.183",
    "sender": [
      {
        "address": "cs@autopass.xyz",
        "name": ""
      }
    ],
    "date": "Sat Nov 08 2025 12:17:22 GMT+0800 (台北標準時間)",
    "from": [
      {
        "address": "cs@autopass.xyz",
        "name": "Autopass 快速通客服團隊"
      }
    ],
    "to": [
      {
        "address": "liencf@gmail.com",
        "name": ""
      }
    ],
    "message-id": "<690ec4521a219_1221aa0802e5@deployment-sidekiq-79b7d5fdf4-fxsmj.mail>",
    "subject": "Autopass 快速通：您的路邊停車訂單收據 (扣款日：2025.11.08)",
    "mime-version": "1.0",
    "content-type": "text/html",
    "content-transfer-encoding": "quoted-printable"
  },
  "attachments": []
}