{
  "index": 978,
  "fromLine": "From peet.ahxcvx@telenet.be Tue Oct 21 03:33:45 2025",
  "subject": "【系統通知】悠遊付帳號年度安全驗證提醒",
  "from": "\"悠遊付 -客服部\" <peet.ahxcvx@telenet.be>",
  "to": "lifeinpaloalto@gmail.com",
  "date": "2025-10-21T03:33:41.000Z",
  "messageId": "<381838423.53157003.1761017621693.JavaMail.zimbra@telenet.be>",
  "topContentType": "[object Object]",
  "mime": {
    "hasText": true,
    "hasHtml": true,
    "attachmentCount": 0
  },
  "headers": {
    "delivered-to": [
      {
        "address": "liencf@gmail.com",
        "name": ""
      }
    ],
    "received": "by 2002:a05:7010:8da6:b0:4d4:9739:2b92 with SMTP id gr38csp1457735mdb; Mon, 20 Oct 2025 20:33:45 -0700 (PDT),from cantor.telenet-ops.be (cantor.telenet-ops.be. [2a02:1800:120:4::f00:10]) by mx.google.com with ESMTPS id ffacd0b85a97d-427ea5a0a6asi4511709f8f.179.2025.10.20.20.33.44 for <liencf@gmail.com> (version=TLS1_3 cipher=TLS_AES_256_GCM_SHA384 bits=256/256); Mon, 20 Oct 2025 20:33:45 -0700 (PDT),from xavier.telenet-ops.be (xavier.telenet-ops.be [IPv6:2a02:1800:120:4::f00:14]) by cantor.telenet-ops.be (Postfix) with ESMTPS id 4crHvX5njHz4x1bp for <liencf@gmail.com>; Tue, 21 Oct 2025 05:33:44 +0200 (CEST),from zcshobo102.telenet-ops.be ([IPv6:2a02:1800:110:86::f00:66]) by xavier.telenet-ops.be with cmsmtp id srZk2F00812TwJU01rZkyk; Tue, 21 Oct 2025 05:33:44 +0200",
    "x-forwarded-encrypted": "i=2; AJvYcCVz5uQbarA2bu6p/VZbb7meV5uTGMVc3dKCrLs+Z54o+dNxJM7Qgi81iSi5jAjyNGp18mM4WOw=@gmail.com",
    "x-google-smtp-source": "AGHT+IGzotp/mcWUkxYAafx0ExnrfZhd03HAOdKEt24zOLIc2s6IIaBeBsoJhTeJRPv2A8AuMa+n",
    "x-received": "by 2002:a05:6000:2911:b0:3e7:46bf:f89d with SMTP id ffacd0b85a97d-42704db22camr11955075f8f.44.1761017625137; Mon, 20 Oct 2025 20:33:45 -0700 (PDT)",
    "arc-seal": "i=1; a=rsa-sha256; t=1761017625; cv=none; d=google.com; s=arc-20240605; b=VP9vPuomCHn+E5Rsem7JzXKlChGVSOg/WbugRgxbB3VNCfJI/j1lGOWYyBuT9W1791 agg8SKApT4D91DR5scKq14BoODW0A3/jcdbcOl8zTEHK61Hx+9Fvu2WhL/xyndSpZxgG oZWi5oXDhNWQSFidnI3seft0+ygRSp3NckWC9/Ld8s6OrIEz6fYSMpOFzob8h3WbPWug z36/6JEMrSdyeOxkl+x4XhyGNX69sMnB3qkVafj2g7L97p35VLA3cplHsg89P/BAPc4q VKcJ9VUhnik3lDrP6iwrmHpWgD3n9vtS16x9VnlHMVgdYlPGTZJrOqHepZHOJV4An41d eKhw==",
    "arc-message-signature": "i=1; a=rsa-sha256; c=relaxed/relaxed; d=google.com; s=arc-20240605; h=dkim-signature:thread-topic:thread-index:mime-version:subject :message-id:to:from:date; bh=Nc91QWRUDRYPQmUGVUMs5EBoXAN8XcSonJvK6rWrBnw=; fh=A7RGuci3+Y/RRih2mgqbogBaXCFpTmBYTiE+3QhaDsM=; b=M10boXOJAffPZLmSbmzNvzp6UxXGNc5Hl0wYIogU3IsBSAnXjwkDXi7N1H2ptuX44o pMn9IfSsqjKZhxAIli8L0seQS6xRCRtQFAE31nTAfKsq4mAiP+Si/rrKIXzGmenPkHY2 UV0ZVM/R8jJThvCWq4o5zlU9NgxgsdhY04L6wsCVL6aRDMbMH69m/V+6WZP/6ShdhKYS 5loZdB2ta0Tzm+FstohhX9y+GFe8SQB3WrqBr88baWJ7WeFIu91/H5ZmVTQ2P0B38ztU 5XsoEUoy0SVTWFCIpx3CN2zM9g6S007DSukzgZJ5XEHBDuxfM4Y8Vz9Ok9748quibVHh RFzg==; dara=google.com",
    "arc-authentication-results": "i=1; mx.google.com; dkim=pass header.i=@telenet.be header.s=r25 header.b=Wi2o2lFU; spf=pass (google.com: domain of peet.ahxcvx@telenet.be designates 2a02:1800:120:4::f00:10 as permitted sender) smtp.mailfrom=peet.ahxcvx@telenet.be; dmarc=pass (p=REJECT sp=REJECT dis=NONE) header.from=telenet.be",
    "return-path": [
      {
        "address": "peet.ahxcvx@telenet.be",
        "name": ""
      }
    ],
    "received-spf": "pass (google.com: domain of peet.ahxcvx@telenet.be designates 2a02:1800:120:4::f00:10 as permitted sender) client-ip=2a02:1800:120:4::f00:10;",
    "authentication-results": "mx.google.com; dkim=pass header.i=@telenet.be header.s=r25 header.b=Wi2o2lFU; spf=pass (google.com: domain of peet.ahxcvx@telenet.be designates 2a02:1800:120:4::f00:10 as permitted sender) smtp.mailfrom=peet.ahxcvx@telenet.be; dmarc=pass (p=REJECT sp=REJECT dis=NONE) header.from=telenet.be",
    "date": "Tue Oct 21 2025 11:33:41 GMT+0800 (台北標準時間)",
    "from": [
      {
        "address": "peet.ahxcvx@telenet.be",
        "name": "悠遊付 -客服部"
      }
    ],
    "to": [
      {
        "address": "lifeinpaloalto@gmail.com",
        "name": ""
      }
    ],
    "message-id": "<381838423.53157003.1761017621693.JavaMail.zimbra@telenet.be>",
    "subject": "【系統通知】悠遊付帳號年度安全驗證提醒",
    "mime-version": "1.0",
    "content-type": "multipart/alternative",
    "x-originating-ip": "[::ffff:80.201.30.14]",
    "thread-index": "SYOIkoGmGfCLojC4gehd8SRhfx4HSQ==",
    "thread-topic": "=?utf-8?B?44CQ57O757Wx6YCa55+l44CR5oKg6YGK5LuY5biz6Jmf5bm05bqm5a6J5YWo6amX6K2J5o+Q6YaS?=",
    "dkim-signature": "v=1"
  },
  "attachments": []
}