{
  "index": 981,
  "fromLine": "From RoyalCaribbean@reply.RoyalCaribbeanMarketing.com Mon Oct 20 23:51:31 2025",
  "subject": "Don’t miss the hottest posts from our social feed 🔥",
  "from": "\"Royal Caribbean\" <RoyalCaribbean@reply.RoyalCaribbeanMarketing.com>",
  "to": "LIENCF@GMAIL.COM",
  "date": "2025-10-20T22:54:15.000Z",
  "messageId": "<c364c90b-a644-4e24-8f7e-132a9e3da7a8@las1s04mta1435.xt.local>",
  "topContentType": "[object Object]",
  "mime": {
    "hasText": true,
    "hasHtml": true,
    "attachmentCount": 0
  },
  "headers": {
    "delivered-to": [
      {
        "address": "liencf@gmail.com",
        "name": ""
      }
    ],
    "received": "by 2002:a05:7010:8da6:b0:4d4:9739:2b92 with SMTP id gr38csp1382653mdb; Mon, 20 Oct 2025 16:51:31 -0700 (PDT),from mta6.royalcaribbeanmarketing.com (mta6.royalcaribbeanmarketing.com. [13.111.138.44]) by mx.google.com with ESMTPS id af79cd13be357-891ccac2529si271929085a.56.2025.10.20.16.51.30 for <LIENCF@gmail.com> (version=TLS1_2 cipher=ECDHE-ECDSA-AES128-GCM-SHA256 bits=128/128); Mon, 20 Oct 2025 16:51:31 -0700 (PDT),by mta6.royalcaribbeanmarketing.com id hur5g42fmd4n for <LIENCF@GMAIL.COM>; Mon, 20 Oct 2025 22:54:16 +0000 (envelope-from <bounce-134484_HTML-1549070876-13234732-1332585-30140@bounce.royalcaribbeanmarketing.com>)",
    "x-google-smtp-source": "AGHT+IE6lepjgsssV1HPPpVZ7VrICuNP1q8ASGawX2Uxidpf82hOJCT/TJW3hSM7C0XMFwp5+iMr",
    "x-received": "by 2002:a05:620a:2886:b0:863:696d:e37a with SMTP id af79cd13be357-8907030c838mr1919898785a.44.1761004291143; Mon, 20 Oct 2025 16:51:31 -0700 (PDT)",
    "arc-seal": "i=1; a=rsa-sha256; t=1761004291; cv=none; d=google.com; s=arc-20240605; b=k0biYXIRVpEeCS9g8332j0TycIYcMexVbrZs5/XQmzhOW3WW9ZwC4RYJ8Yf/1T7qTP eazRSodtFvrgvf46baZyQigEI3f2btWPSSKW8RVjREVLoYKRNl868f8L926TkRxkdpea vMDsJOxkscV+knTul07oTXXnVvIQKKMQgH7aZcbNCUi3KZ/YLoIM7vIUzgvjkQuTM37E tEUDPs5yx9gXtcFiNZtKJsPs+YASpEnJhlkZzge5fR4SAIaxprI0zJ6Ohmw/IeJFaUq2 7uQ65+OZNWrz0npYvV45kldLGilonN/Z+NZdO2BMKnpaheTiuC85Gg9uXfPlcT8rk9vx qA7w==",
    "arc-message-signature": "i=1; a=rsa-sha256; c=relaxed/relaxed; d=google.com; s=arc-20240605; h=feedback-id:message-id:reply-to:mime-version:list-unsubscribe-post :list-unsubscribe:date:subject:to:from:dkim-signature:dkim-signature; bh=ScsPk574RiwJJPMydi6vo15iO2dyLQbk8M6IXRxHSoE=; fh=vJ4NSVUPajgSi0/CEKHf5eaby7wPvKNevbuC/lPebKM=; b=WfoCh31BJ/jG1+125v54YJf9ivFpkRxby1lQHTRQp3WS2BekX5JUTKnXg5fk9pa975 IqM31RF1FQtnzLIxA37dRqZ35DDv5xbcjTXuxxSlbxd5HQCvqxyRXYy1XniKQSzHMsaG /ZPxgJG3t/rA/4JYbHTdBbtJwOWC7duKxuMTOjgPxZvVIEsAZwFCFt7u//tkG8L4xuP5 /HjKJY5gwtCvUzJ8tEZnQ0k+XV3LGP2tBxdmUlpYrCjKAuuvOyXKMhQwkkNy76vPsjUg M2XDk0pwoWlsx68lAbU3dSfL4drjcIY+nCAHTZsBYyMw7XrfTC1fhR6RWRhvRjljgOoR 3vDQ==; dara=google.com",
    "arc-authentication-results": "i=1; mx.google.com; dkim=pass header.i=@royalcaribbeanmarketing.com header.s=200608 header.b=\"PzE6Lj2/\"; dkim=pass header.i=@s4.y.mc.salesforce.com header.s=fbldkim4 header.b=\"e/TjoB3i\"; spf=pass (google.com: domain of bounce-134484_html-1549070876-13234732-1332585-30140@bounce.royalcaribbeanmarketing.com designates 13.111.138.44 as permitted sender) smtp.mailfrom=bounce-134484_HTML-1549070876-13234732-1332585-30140@bounce.royalcaribbeanmarketing.com; dmarc=pass (p=REJECT sp=REJECT dis=NONE) header.from=royalcaribbeanmarketing.com",
    "return-path": [
      {
        "address": "bounce-134484_HTML-1549070876-13234732-1332585-30140@bounce.royalcaribbeanmarketing.com",
        "name": ""
      }
    ],
    "received-spf": "pass (google.com: domain of bounce-134484_html-1549070876-13234732-1332585-30140@bounce.royalcaribbeanmarketing.com designates 13.111.138.44 as permitted sender) client-ip=13.111.138.44;",
    "authentication-results": "mx.google.com; dkim=pass header.i=@royalcaribbeanmarketing.com header.s=200608 header.b=\"PzE6Lj2/\"; dkim=pass header.i=@s4.y.mc.salesforce.com header.s=fbldkim4 header.b=\"e/TjoB3i\"; spf=pass (google.com: domain of bounce-134484_html-1549070876-13234732-1332585-30140@bounce.royalcaribbeanmarketing.com designates 13.111.138.44 as permitted sender) smtp.mailfrom=bounce-134484_HTML-1549070876-13234732-1332585-30140@bounce.royalcaribbeanmarketing.com; dmarc=pass (p=REJECT sp=REJECT dis=NONE) header.from=royalcaribbeanmarketing.com",
    "dkim-signature": "[object Object],[object Object]",
    "from": [
      {
        "address": "RoyalCaribbean@reply.RoyalCaribbeanMarketing.com",
        "name": "Royal Caribbean"
      }
    ],
    "to": [
      {
        "address": "LIENCF@GMAIL.COM",
        "name": ""
      }
    ],
    "subject": "Don’t miss the hottest posts from our social feed 🔥",
    "date": "Tue Oct 21 2025 06:54:15 GMT+0800 (台北標準時間)",
    "list": "[object Object]",
    "mime-version": "1.0",
    "reply-to": [
      {
        "address": "reply-fe6615737767007a7616-134484_HTML-1549070876-1332585-30140@reply.RoyalCaribbeanMarketing.com",
        "name": "Royal Caribbean"
      }
    ],
    "x-sfmc-stack": "4",
    "x-job": "1332585_13234732",
    "message-id": "<c364c90b-a644-4e24-8f7e-132a9e3da7a8@las1s04mta1435.xt.local>",
    "feedback-id": "1332585:13234732:13.111.138.44:sfmktgcld",
    "content-type": "multipart/alternative"
  },
  "attachments": []
}