{
  "index": 895,
  "fromLine": "From contact@mailer.humblebundle.com Wed Oct 22 20:11:07 2025",
  "subject": "Our Star Wars bundle is fully operational 👀",
  "from": "\"Humble Bundle\" <contact@mailer.humblebundle.com>",
  "to": "liencf@gmail.com",
  "date": "2025-10-22T20:11:07.000Z",
  "messageId": "<20251022201107.b166929ea48067af@mailer.humblebundle.com>",
  "topContentType": "[object Object]",
  "mime": {
    "hasText": true,
    "hasHtml": true,
    "attachmentCount": 0
  },
  "headers": {
    "delivered-to": [
      {
        "address": "liencf@gmail.com",
        "name": ""
      }
    ],
    "received": "by 2002:a05:7010:8da6:b0:4d4:9739:2b92 with SMTP id gr38csp2583772mdb; Wed, 22 Oct 2025 13:11:08 -0700 (PDT),from d150.c153.cordialmail.net (d150.c153.cordialmail.net. [192.112.153.150]) by mx.google.com with UTF8SMTPS id 41be03b00d2f7-b6acf7dbfffsi5898294a12.1432.2025.10.22.13.11.07 for <liencf@gmail.com> (version=TLS1_2 cipher=ECDHE-ECDSA-AES128-GCM-SHA256 bits=128/128); Wed, 22 Oct 2025 13:11:07 -0700 (PDT),by 49df59bb2a1e768eebc6d8d901b857dcca2d64e5836d21ba38a21655149e007e with HTTP id 68f93a5be3fe6075d7210e54; Wed, 22 Oct 2025 20:11:07 GMT",
    "x-google-smtp-source": "AGHT+IFLih8nI/ew/pf/UODMd+lfJJoNhhcciH8t7hsI0knyxGoP1cOKOoqKDbNry6/aAFF2Xmft",
    "x-received": "by 2002:a05:6a21:3396:b0:251:43f5:caba with SMTP id adf61e73a8af0-334a862e2ccmr28476064637.53.1761163867984; Wed, 22 Oct 2025 13:11:07 -0700 (PDT)",
    "arc-seal": "i=1; a=rsa-sha256; t=1761163867; cv=none; d=google.com; s=arc-20240605; b=Ruwoz1JVOalCl60DC8LS1bYeiCCHDDH10/6JZ++X+dlkeiAoAff3E2FiaZObATs/vy MzDIpuZqwFW8o2Qdd5aflPrUeqLHi/f1rduUOwXrmtqPuialr6WjUercw/79bfXGChaE DNcZBrqRIjjqXzMKbcpstchSsqlok9Ufr27gtG2yU3C08A8R57SJEJZDY6+MWlEBMBwU Ac7GvbphMe1ZplMxNdYJu2sIuhrYHUq4kwodMDbMG29gGr3JJg7AjLAfYHdJHVRfjo+k OKrwRuoCvl+BXdbmz6GFHAdvrLeth0Y0OKjVqbvF1r9XnUVzMaqTVyap+NSfHYiIglSN 7gZQ==",
    "arc-message-signature": "i=1; a=rsa-sha256; c=relaxed/relaxed; d=google.com; s=arc-20240605; h=content-transfer-encoding:message-id:reply-to:bimi-selector:to:from :subject:mime-version:date:sender:list-unsubscribe :list-unsubscribe-post:dkim-signature:dkim-signature; bh=ztqbxokibOMNDrnJzFQe79/Er6zNn1isZtnMZcNnPRs=; fh=hnWLqYXx/enUl3blN9H38oqkLIXAr0tyRzvlFpRYzeI=; b=UqvRXMeFlVVGlZHBHUic65/AIPu6ryWyPEFT1QSK6ixisiNzDl9FCTdz9go0DKIaeB da7z9+HvQvpA22a3bq8zwCSL++Blp6XvIyV+IOwAjpTtJtdE1QiTahXLb2ZEJ4ZkwYZi n/BFVMqn2ote+Mh6WDI99Fpd8cyIf/Q4EoeE6sRx4G1ZlwtCKPGFlrU6dyONWX3dR8sE QUxdVJKcMU4Wt+VrodiDdiQNKD8awHIMgOv09JDo8Zvn1lK5TTkdNgoCnnRolwoXFHD0 gSGoCLb2zaUJFcleWZQ2sfVMF95m50BzzwY5R95Du9MnX2CWQJE6vNYDNKEm+5nTUSEK nGdg==; dara=google.com",
    "arc-authentication-results": "i=1; mx.google.com; dkim=pass header.i=@mailer.humblebundle.com header.s=crdl01 header.b=pmz9OAjc; dkim=pass header.i=@mailgun.org header.s=mg header.b=bJ5ruhJk; spf=pass (google.com: domain of bounce+e250bd.460f1c-liencf=gmail.com@mailer.humblebundle.com designates 192.112.153.150 as permitted sender) smtp.mailfrom=\"bounce+e250bd.460f1c-liencf=gmail.com@mailer.humblebundle.com\"; dmarc=pass (p=QUARANTINE sp=QUARANTINE dis=NONE) header.from=humblebundle.com",
    "return-path": [
      {
        "address": "bounce+e250bd.460f1c-liencf=gmail.com@mailer.humblebundle.com",
        "name": ""
      }
    ],
    "received-spf": "pass (google.com: domain of bounce+e250bd.460f1c-liencf=gmail.com@mailer.humblebundle.com designates 192.112.153.150 as permitted sender) client-ip=192.112.153.150;",
    "authentication-results": "mx.google.com; dkim=pass header.i=@mailer.humblebundle.com header.s=crdl01 header.b=pmz9OAjc; dkim=pass header.i=@mailgun.org header.s=mg header.b=bJ5ruhJk; spf=pass (google.com: domain of bounce+e250bd.460f1c-liencf=gmail.com@mailer.humblebundle.com designates 192.112.153.150 as permitted sender) smtp.mailfrom=\"bounce+e250bd.460f1c-liencf=gmail.com@mailer.humblebundle.com\"; dmarc=pass (p=QUARANTINE sp=QUARANTINE dis=NONE) header.from=humblebundle.com",
    "dkim-signature": "[object Object],[object Object]",
    "x-mailgun-sid": "WyI5MzA1MiIsImxpZW5jZkBnbWFpbC5jb20iLCI0NjBmMWMiXQ==",
    "list": "[object Object]",
    "x-feedback-id": "contact@mailer.humblebundle.com:msID:102:68f906466f5b83de170f9121:ot:66f4b28391616c98ca622260:mailgun,102:102_68f906466f5b83de170f9121_ot:5fa2077a730d25f072bfb2e3:cordial",
    "x-mailgun-sending-ip-pool-name": "hb-d",
    "x-mailgun-sending-ip-pool": "66f46832e4fa9b2444147fb3",
    "x-mailgun-sending-ip": "192.112.153.150",
    "sender": [
      {
        "address": "contact@mailer.humblebundle.com",
        "name": ""
      }
    ],
    "date": "Thu Oct 23 2025 04:11:07 GMT+0800 (台北標準時間)",
    "mime-version": "1.0",
    "subject": "Our Star Wars bundle is fully operational 👀",
    "from": [
      {
        "address": "contact@mailer.humblebundle.com",
        "name": "Humble Bundle"
      }
    ],
    "to": [
      {
        "address": "liencf@gmail.com",
        "name": ""
      }
    ],
    "x-mailgun-tag": "msID:102:68f906466f5b83de170f9121:ot",
    "x-mailgun-track-opens": "true",
    "bimi-selector": "v=BIMI1; s=default;",
    "x-crdl-mc": "102:68f906466f5b83de170f9121:ot:5fa2077a730d25f072bfb2e3:1",
    "reply-to": [
      {
        "address": "contact@humblebundle.com",
        "name": ""
      }
    ],
    "x-mailgun-variables": "{\"crdlEnv\": \"production\", \"mcID\": \"102:68f906466f5b83de170f9121:ot:5fa2077a730d25f072bfb2e3:1\"}",
    "message-id": "<20251022201107.b166929ea48067af@mailer.humblebundle.com>",
    "content-type": "text/html",
    "content-transfer-encoding": "quoted-printable"
  },
  "attachments": []
}