{
  "index": 970,
  "fromLine": "From hulu@hulumail.com Tue Oct 21 08:56:21 2025",
  "subject": "New Sign-in to Your Account",
  "from": "\"Hulu\" <hulu@hulumail.com>",
  "to": "liencf@gmail.com",
  "date": "2025-10-21T08:56:18.000Z",
  "messageId": "<62c8ac1d-6bea-47fb-a4c9-7e1c80322464@las1s04mta1602.xt.local>",
  "topContentType": "[object Object]",
  "mime": {
    "hasText": true,
    "hasHtml": true,
    "attachmentCount": 0
  },
  "headers": {
    "delivered-to": [
      {
        "address": "liencf@gmail.com",
        "name": ""
      }
    ],
    "received": "by 2002:a05:7010:8da6:b0:4d4:9739:2b92 with SMTP id gr38csp1561090mdb; Tue, 21 Oct 2025 01:56:22 -0700 (PDT),from mta3.hulumail.com (mta3.hulumail.com. [13.111.11.59]) by mx.google.com with ESMTPS id 41be03b00d2f7-b6a76b1d578si5183359a12.505.2025.10.21.01.56.20 for <liencf@gmail.com> (version=TLS1_2 cipher=ECDHE-ECDSA-AES128-GCM-SHA256 bits=128/128); Tue, 21 Oct 2025 01:56:21 -0700 (PDT),by mta3.hulumail.com id hut5ba2fmd44 for <liencf@gmail.com>; Tue, 21 Oct 2025 08:56:18 +0000 (envelope-from <bounce-48_HTML-1010190083-5063827-1064447-7269054@bounce.hulumail.com>)",
    "x-google-smtp-source": "AGHT+IEZT6ahkJuh0qY53rnuulsTw+zxNgze9i5UFAxwA0LOGSKsijEZRaaf2yW3n1jPUrjLmeo9",
    "x-received": "by 2002:a05:6a20:3c8d:b0:334:7bce:8394 with SMTP id adf61e73a8af0-334a8614916mr19641535637.51.1761036982019; Tue, 21 Oct 2025 01:56:22 -0700 (PDT)",
    "arc-seal": "i=1; a=rsa-sha256; t=1761036982; cv=none; d=google.com; s=arc-20240605; b=MW6rE4VWVP1DHUm2OfhhE58cu6FCbjRTe1ZtKoCqRVO4kDRp6JL73XFdJJIRpK4Qf6 DNR/Ph8M6JQgC36R5IOZ2RCVnQLOZl5A7JTlGPRT8J7htcK0/pBNLuWHV31gjMIs8Stk PltSvt5vDJ91TaadaXDM8M1f+iXKZPN8kMuDaZ9IVYs2k8afSYvBqvjMJ3cWMtNcqzXG vOoLPnFxHlppbfSUCWsLsXUw9bjd7rHncoSJpcEXydvczE7GcZMXdIOtQXE22B3y/VrA GQvdI4wMHdDBU8NMimRu+gtvRNep3XiGhIn7Hj5JDJW6fxejV4Fn0ahOaBX0u9SRzXE2 JA1A==",
    "arc-message-signature": "i=1; a=rsa-sha256; c=relaxed/relaxed; d=google.com; s=arc-20240605; h=content-transfer-encoding:feedback-id:message-id:reply-to :mime-version:list-help:date:subject:to:from:dkim-signature :dkim-signature; bh=RW7nzZg7igUkbV0FRpfN3fWa4zFkowI+tAT30/Jjj/0=; fh=AuRPPJxWT3oDWns/IAyV12DuHusfebFT2kEqOaRmmSo=; b=R9LjxYEtjDlB6FD9jbS7no0QiMZTtPgUd/pwO2KkpS+eTt6PZnOVy+yZ1WLFW/Pi6F 9yiimhvJASdmvQxQHJDRDpRzxMd4CcYzmONroO4wBkZc+r3603aHY57ZvrVRDaTFzkfD JKjx84RlfU4ZOVy2S2aSH7fZiCsVN7kei0OQxPG923yrs3Jn31Ol0Ke7OwKFOeczgE1n 9rTm+FFOhZ/eaplYMzDe0OIVCi4x0TG1834VVr7cdzu7GXoNG9j1USsGDxAxRgH55xW0 hlbj/IwZJL45CQ8tnCy8ACa9x+c4mRrNq6qY5JiUBDOF4h/hXXfbnzlcKFHoaNKcMLqR RB3A==; dara=google.com",
    "arc-authentication-results": "i=1; mx.google.com; dkim=pass header.i=@hulumail.com header.s=200608 header.b=KRP9uKAR; dkim=pass header.i=@s4.y.mc.salesforce.com header.s=fbldkim4 header.b=IU+6N6gx; spf=pass (google.com: domain of bounce-48_html-1010190083-5063827-1064447-7269054@bounce.hulumail.com designates 13.111.11.59 as permitted sender) smtp.mailfrom=bounce-48_HTML-1010190083-5063827-1064447-7269054@bounce.hulumail.com; dmarc=pass (p=NONE sp=NONE dis=NONE) header.from=hulumail.com",
    "return-path": [
      {
        "address": "bounce-48_HTML-1010190083-5063827-1064447-7269054@bounce.hulumail.com",
        "name": ""
      }
    ],
    "received-spf": "pass (google.com: domain of bounce-48_html-1010190083-5063827-1064447-7269054@bounce.hulumail.com designates 13.111.11.59 as permitted sender) client-ip=13.111.11.59;",
    "authentication-results": "mx.google.com; dkim=pass header.i=@hulumail.com header.s=200608 header.b=KRP9uKAR; dkim=pass header.i=@s4.y.mc.salesforce.com header.s=fbldkim4 header.b=IU+6N6gx; spf=pass (google.com: domain of bounce-48_html-1010190083-5063827-1064447-7269054@bounce.hulumail.com designates 13.111.11.59 as permitted sender) smtp.mailfrom=bounce-48_HTML-1010190083-5063827-1064447-7269054@bounce.hulumail.com; dmarc=pass (p=NONE sp=NONE dis=NONE) header.from=hulumail.com",
    "dkim-signature": "[object Object],[object Object]",
    "from": [
      {
        "address": "hulu@hulumail.com",
        "name": "Hulu"
      }
    ],
    "to": [
      {
        "address": "liencf@gmail.com",
        "name": ""
      }
    ],
    "subject": "New Sign-in to Your Account",
    "date": "Tue Oct 21 2025 16:56:18 GMT+0800 (台北標準時間)",
    "list": "[object Object]",
    "mime-version": "1.0",
    "reply-to": [
      {
        "address": "reply-fe90117073670c7f72-48_HTML-1010190083-1064447-7269054@hulumail.com",
        "name": "Hulu"
      }
    ],
    "x-sfmc-stack": "4",
    "x-job": "1064447_5063827",
    "message-id": "<62c8ac1d-6bea-47fb-a4c9-7e1c80322464@las1s04mta1602.xt.local>",
    "feedback-id": "1064447:5063827:13.111.11.59:sfmktgcld",
    "content-type": "text/html",
    "content-transfer-encoding": "8bit"
  },
  "attachments": []
}