{
  "index": 166,
  "fromLine": "From service@mhu.taipeifubon.com.tw Wed Nov 12 11:45:11 2025",
  "subject": "【活動即將截止】Fubon+繳地價稅，首次繳費回饋5%!!(限用帳戶繳費)",
  "from": "\"台北富邦銀行\" <service@mhu.taipeifubon.com.tw>",
  "to": "liencf@gmail.com",
  "date": "2025-11-12T10:01:40.000Z",
  "messageId": "<9d40a5fe32bc6b08@9b74cf5103fe416c>",
  "topContentType": "[object Object]",
  "mime": {
    "hasText": true,
    "hasHtml": true,
    "attachmentCount": 0
  },
  "headers": {
    "delivered-to": [
      {
        "address": "liencf@gmail.com",
        "name": ""
      }
    ],
    "received": "by 2002:a05:7010:8883:b0:4ec:41ca:fc70 with SMTP id ee3csp68720mdb; Wed, 12 Nov 2025 03:45:11 -0800 (PST),from mhu.taipeifubon.com.tw (mhu.taipeifubon.com.tw. [219.87.145.5]) by mx.google.com with ESMTPS id d9443c01a7336-2984dc9fcd2si14226735ad.403.2025.11.12.03.45.10 for <liencf@gmail.com> (version=TLS1_2 cipher=ECDHE-ECDSA-AES128-GCM-SHA256 bits=128/128); Wed, 12 Nov 2025 03:45:11 -0800 (PST)",
    "x-google-smtp-source": "AGHT+IHG+fuLDYGOcZaiRa9Vvz0rwzwXWPUaaqvP36wAAQnrDY2FF7SU5NV7st8R1f08TUOInTQ/",
    "x-received": "by 2002:a17:903:1103:b0:295:f47:75cb with SMTP id d9443c01a7336-2984ed95005mr36573375ad.23.1762947911155; Wed, 12 Nov 2025 03:45:11 -0800 (PST)",
    "arc-seal": "i=1; a=rsa-sha256; t=1762947911; cv=none; d=google.com; s=arc-20240605; b=PUtL5NdflFY1DkmldzB7sFeOtW+bIC1/rj7YnV/sc8tpLj4eNKuXUtu0ADIZeiiWrd sQ5N0L3iczSY0f5NxTI65FHXUEfh4L8oPVziyJ4cjGhdRpw/g0btrnvfrikxNat4mzhx YJupJQn7zFwoZD1NmtOKyIK4uy9exF1gc2eBlwOiDr11LnMOiqbgieZG71d6NLisjPlO WHHOo5kjofwjzCzBSUlvR6eCijQSQkHV0imYTjVpxx0+Tpeh0xFFr+mzGNYfRfVID2M6 cGTn+iQ5hws3sVilsj+AzZ1WS0JOvxhvMEBiw96WBABvfSuIDoPn+h2vNSTy4aRCPgnY MZ3w==",
    "arc-message-signature": "i=1; a=rsa-sha256; c=relaxed/relaxed; d=google.com; s=arc-20240605; h=content-transfer-encoding:thread-index:precedence:subject:reply-to :to:from:date:message-id:mime-version:dkim-signature; bh=D0jxtELibb5dhGd6qq+T4dxey8KqBZvWpxF3alWm3zg=; fh=hnWLqYXx/enUl3blN9H38oqkLIXAr0tyRzvlFpRYzeI=; b=OSM4jS8zmQBy0v3AsQA4PeCFkJzrm9btjKcdWg7L66Xjf+cRJd34T1mqGJ2yi5ufGa 447Ie0TbmNHAvHqy7RKCudNklDNOE9hSGpCnwSiAu1Ja+eUrelJMKBBfoJGq+TihumNl lg/FoH/Jr95WF8HV+NbXTP8lbF5gXm0cpfiF+A9JuMzoCPN7vC25GTANTps+NXCy/wxJ cIpq5FYSHGtcRVZW9slrbZo085DohzjerjI6l7tkp/NyipH04qg+BzpLB5LkflRuLBHI LYPaqF0L2KnHBBoccFi5BooYc0DCVEQXhOvZe2EizRvGPELnTZTBGgwVJOjcLaA5a5fN triw==; dara=google.com",
    "arc-authentication-results": "i=1; mx.google.com; dkim=pass header.i=@mhu.taipeifubon.com.tw header.s=mhu header.b=kGK4nfnU; spf=pass (google.com: domain of service@mhu.taipeifubon.com.tw designates 219.87.145.5 as permitted sender) smtp.mailfrom=service@mhu.taipeifubon.com.tw; dmarc=pass (p=NONE sp=NONE dis=NONE) header.from=mhu.taipeifubon.com.tw",
    "return-path": [
      {
        "address": "service@mhu.taipeifubon.com.tw",
        "name": ""
      }
    ],
    "received-spf": "pass (google.com: domain of service@mhu.taipeifubon.com.tw designates 219.87.145.5 as permitted sender) client-ip=219.87.145.5;",
    "authentication-results": "mx.google.com; dkim=pass header.i=@mhu.taipeifubon.com.tw header.s=mhu header.b=kGK4nfnU; spf=pass (google.com: domain of service@mhu.taipeifubon.com.tw designates 219.87.145.5 as permitted sender) smtp.mailfrom=service@mhu.taipeifubon.com.tw; dmarc=pass (p=NONE sp=NONE dis=NONE) header.from=mhu.taipeifubon.com.tw",
    "dkim-signature": "v=1",
    "mime-version": "1.0",
    "message-id": "<9d40a5fe32bc6b08@9b74cf5103fe416c>",
    "date": "Wed Nov 12 2025 18:01:40 GMT+0800 (台北標準時間)",
    "from": [
      {
        "address": "service@mhu.taipeifubon.com.tw",
        "name": "台北富邦銀行"
      }
    ],
    "to": [
      {
        "address": "liencf@gmail.com",
        "name": ""
      }
    ],
    "reply-to": [
      {
        "address": "server@fubon.com",
        "name": ""
      }
    ],
    "subject": "【活動即將截止】Fubon+繳地價稅，首次繳費回饋5%!!(限用帳戶繳費)",
    "x-assurancesys-bulkmail": "1",
    "precedence": "bulk",
    "thread-index": "MjI3NDIxXzI5MTUzMDM2Mg==",
    "content-type": "text/html",
    "content-transfer-encoding": "quoted-printable"
  },
  "attachments": []
}