{
  "index": 125,
  "fromLine": "From hi@spellar.ai Thu Nov 13 06:13:39 2025",
  "subject": "Spellar AI - Here Is Your Meeting Summary",
  "from": "hi@spellar.ai",
  "to": "liencf@gmail.com",
  "date": "2025-11-13T06:13:39.000Z",
  "messageId": "<iLaUnN3mRKe9fwVLL8LCrA@geopod-ismtpd-37>",
  "topContentType": "[object Object]",
  "mime": {
    "hasText": true,
    "hasHtml": true,
    "attachmentCount": 0
  },
  "headers": {
    "delivered-to": [
      {
        "address": "liencf@gmail.com",
        "name": ""
      }
    ],
    "received": "by 2002:a05:7010:8883:b0:4ec:41ca:fc70 with SMTP id ee3csp635767mdb; Wed, 12 Nov 2025 22:13:40 -0800 (PST),from o1.ptr9173.spellar.ai (o1.ptr9173.spellar.ai. [167.89.79.176]) by mx.google.com with ESMTPS id d75a77b69052e-4ede88d61dfsi4001361cf.898.2025.11.12.22.13.39 for <liencf@gmail.com> (version=TLS1_3 cipher=TLS_AES_128_GCM_SHA256 bits=128/128); Wed, 12 Nov 2025 22:13:39 -0800 (PST),by recvd-7f4fb8995-kn4l4 with SMTP id recvd-7f4fb8995-kn4l4-1-69157713-E 2025-11-13 06:13:39.424130616 +0000 UTC m=+13958944.477477336,from NDA2ODgxMTc (unknown) by geopod-ismtpd-37 (SG) with HTTP id iLaUnN3mRKe9fwVLL8LCrA Thu, 13 Nov 2025 06:13:39.344 +0000 (UTC)",
    "x-google-smtp-source": "AGHT+IGnuH+dMlDJwO5PeQRNy6CTxOoaFbePjHZMfz3gt/9BDEubHMGchC7wMarHnT2UwF/iQwG/",
    "x-received": "by 2002:ac8:5712:0:b0:4eb:a1cb:7c with SMTP id d75a77b69052e-4eddbd9d1b5mr76772661cf.64.1763014419875; Wed, 12 Nov 2025 22:13:39 -0800 (PST)",
    "arc-seal": "i=1; a=rsa-sha256; t=1763014419; cv=none; d=google.com; s=arc-20240605; b=H1ITyP9vc6COH0jTBb8k7xB/5FX9n7d5JGS+OJ4xRHq6U/75rbNFTfbBpDehfXzfs4 JaRoGRYxepi2qD5hWM/fAa8aUgPMAFDZ3JsAWrhfQEiSNizfStkkd6e5LRczb9raQYnU /a089McsF7I9x+1ypJhFLWKQRXx/sXBqeEuMk3TBs8y/T4zJ0QEH1UbW0MnXs2cYbhVv 1mIAHlxpHuZOLLEInhP52j6WEIKInyTBEjsE5SyVIUJtfeiUfOfBJKXDtAIZY4MGb7mZ noVnioCOW8dWStRdOXgbw2GJ2WeMCk/ZwOAdyO12NUUg97+GZNVCR0RXq69xD7Zl+EON nGHA==",
    "arc-message-signature": "i=1; a=rsa-sha256; c=relaxed/relaxed; d=google.com; s=arc-20240605; h=list-unsubscribe-post:list-unsubscribe:to:subject:message-id :mime-version:from:date:dkim-signature:dkim-signature; bh=e6F8ZXtf5w8H8gkGwx+3E3AmnDzjMAginnSHuUHmrqU=; fh=hnWLqYXx/enUl3blN9H38oqkLIXAr0tyRzvlFpRYzeI=; b=Fp7OFGMBi+OWkjNgvul7tE+HfhNvvaw27v7Fou75P9iWXc1ZktE4E4k1kfbH7hfrR5 S0JWBErms2HRBClB0thdTIj+So1MED24eINm2Knr+Tk+UEld98E+9dUA9hOybvfz/y3Y 6u2ZkKw6QMHDMhyS4Lx/LtdEQljovpiZsnSnozNhO5tBehBS2j3kzgg8wO9kQltXTugo DO/lmay3IcqMnWerrpxEsiKy6eDvWhdZZjPSvqB/1uJMp+LGdRvdf+4ogABca8AYZij6 zr7Dwc0HaBqM/7y984WSNx305740hKzThydaeCizFqVrruTNtolXpqGmrXsloxcwlhIF Y3BA==; dara=google.com",
    "arc-authentication-results": "i=1; mx.google.com; dkim=pass header.i=@spellar.ai header.s=s1 header.b=mZaZACbP; dkim=pass header.i=@sendgrid.info header.s=smtpapi header.b=UG+kWXUc; spf=pass (google.com: domain of bounces+40688117-d73e-liencf=gmail.com@em6526.spellar.ai designates 167.89.79.176 as permitted sender) smtp.mailfrom=\"bounces+40688117-d73e-liencf=gmail.com@em6526.spellar.ai\"; dmarc=pass (p=QUARANTINE sp=QUARANTINE dis=NONE) header.from=spellar.ai",
    "return-path": [
      {
        "address": "bounces+40688117-d73e-liencf=gmail.com@em6526.spellar.ai",
        "name": ""
      }
    ],
    "received-spf": "pass (google.com: domain of bounces+40688117-d73e-liencf=gmail.com@em6526.spellar.ai designates 167.89.79.176 as permitted sender) client-ip=167.89.79.176;",
    "authentication-results": "mx.google.com; dkim=pass header.i=@spellar.ai header.s=s1 header.b=mZaZACbP; dkim=pass header.i=@sendgrid.info header.s=smtpapi header.b=UG+kWXUc; spf=pass (google.com: domain of bounces+40688117-d73e-liencf=gmail.com@em6526.spellar.ai designates 167.89.79.176 as permitted sender) smtp.mailfrom=\"bounces+40688117-d73e-liencf=gmail.com@em6526.spellar.ai\"; dmarc=pass (p=QUARANTINE sp=QUARANTINE dis=NONE) header.from=spellar.ai",
    "dkim-signature": "[object Object],[object Object]",
    "content-type": "multipart/alternative",
    "date": "Thu Nov 13 2025 14:13:39 GMT+0800 (台北標準時間)",
    "from": [
      {
        "address": "hi@spellar.ai",
        "name": ""
      }
    ],
    "mime-version": "1.0",
    "message-id": "<iLaUnN3mRKe9fwVLL8LCrA@geopod-ismtpd-37>",
    "subject": "Spellar AI - Here Is Your Meeting Summary",
    "x-sg-eid": "=?us-ascii?Q?u001=2E3o2tnQRu2PdlsFd5MFuTRMbg3ScjVnNL+RW=2FjVVUt5dFja=2FvmF65rPRqC?= =?us-ascii?Q?oc3Qd3LP6DjPYZoeO4dnhRBAxXxPavFqfZcu9=2Fu?= =?us-ascii?Q?fR94yJjNK12bDjNn1IPrbaXdyrI31xcXrsBvN8I?= =?us-ascii?Q?7h738cLEemw8lZuk=2Fe5W4sLS4Ltx+X3+6ECl1sm?= =?us-ascii?Q?rgnkloI4FQ9QmYLycQ?=",
    "x-sg-id": "=?us-ascii?Q?u001=2ESdBcvi+Evd=2FbQef8eZF3BiMiW+ZUaaDoZonh1xKFny7iD2rV9eo5vkyJ7?= =?us-ascii?Q?C1G11uSsIfTAjgHd0ggLPbr8FlEQS8+wsa4b62b?= =?us-ascii?Q?QjjDtJHPxZ4hWwuC=2FAJLYwRltU0uUv8QDcLfB=2Fq?= =?us-ascii?Q?2wo1+gTAJU8tmiaVQcBZR6wSnzj0hWKJtxtDxGW?= =?us-ascii?Q?Boz8yG6J7LsI9jp83W74BuvYOlxi0Y1mu9a6d0L?= =?us-ascii?Q?Q=3D=3D?=",
    "to": [
      {
        "address": "liencf@gmail.com",
        "name": ""
      }
    ],
    "x-entity-id": "u001.suPxF1vNDoECBcy8PojQpA==",
    "list": "[object Object]"
  },
  "attachments": []
}