{
  "index": 48,
  "fromLine": "From noreply@md.getsentry.com Sat Nov 15 18:38:55 2025",
  "subject": "Weekly Report for Xamide: November 8th, 2025 - November 15th, 2025",
  "from": "\"Sentry\" <noreply@md.getsentry.com>",
  "to": "liencf@gmail.com",
  "date": "2025-11-15T18:38:54.000Z",
  "messageId": "<20251115183853.608487.19199@md.getsentry.com>",
  "topContentType": "[object Object]",
  "mime": {
    "hasText": false,
    "hasHtml": true,
    "attachmentCount": 0
  },
  "headers": {
    "delivered-to": [
      {
        "address": "liencf@gmail.com",
        "name": ""
      }
    ],
    "received": "by 2002:a05:7010:8883:b0:4ec:41ca:fc70 with SMTP id ee3csp2411632mdb; Sat, 15 Nov 2025 10:38:56 -0800 (PST),from o3.md.getsentry.com (o3.md.getsentry.com. [167.89.84.75]) by mx.google.com with ESMTPS id 41be03b00d2f7-bc375830026si4082434a12.505.2025.11.15.10.38.55 for <liencf@gmail.com> (version=TLS1_3 cipher=TLS_AES_128_GCM_SHA256 bits=128/128); Sat, 15 Nov 2025 10:38:55 -0800 (PST),by recvd-664f5cd8bb-mtdj4 with SMTP id recvd-664f5cd8bb-mtdj4-1-6918C8BE-A 2025-11-15 18:38:54.47361986 +0000 UTC m=+1020814.053193546,from task-default-worker-756b55f7c5-6x4j6 (unknown) by geopod-ismtpd-11 (SG) with ESMTP id iy9O4P-1ROi9DSSrW-VOpQ for <liencf@gmail.com>; Sat, 15 Nov 2025 18:38:54.389 +0000 (UTC)",
    "x-google-smtp-source": "AGHT+IF1Riez3wuihGgZ0lU3uI4W0DWRYCP1RIlT1SqSMw+rv4Gwd/6E0DKrVuv0lPSs098Utdk1",
    "x-received": "by 2002:a05:6a20:244b:b0:35d:8c8:8ab4 with SMTP id adf61e73a8af0-35d08c88c4emr3836707637.44.1763231935931; Sat, 15 Nov 2025 10:38:55 -0800 (PST)",
    "arc-seal": "i=1; a=rsa-sha256; t=1763231935; cv=none; d=google.com; s=arc-20240605; b=gpDXOKKao2Ag4WqJe6shwk90RWirVX/K2DaVGk/tOUmbrMWGzPW+EOpxVDiDo7HJh9 bgr4vgLY7thLRRYznHMMeOQY2Ts6SdNOWtWVjaflnmp7pTDeLTYJgKWFBhS4xUnrDxLV jRuKJa+juMiBFnWwytyU0P64L9Mj63rffC1mAFIcs5NR6pcxxkj2UFnl3ywe3KC1L+BX TWu8FbVHSwj6HSJZrLZ4QQM6gv6tPyPf7Mo1Z+vJovWc1UN4qzHw9WGIbowBO7YU/TXY /8DTsvqt73mdMjpIt57K+1txoo0i32FcTZcJkmk+41mfchzohQ2SHK7UBetUhmwz6oRF qd1w==",
    "arc-message-signature": "i=1; a=rsa-sha256; c=relaxed/relaxed; d=google.com; s=arc-20240605; h=to:message-id:date:from:subject:mime-version:dkim-signature :dkim-signature; bh=ofpY/icbGfWM9oD6QISvYr4lue64lwB/laSqWKb6Eyk=; fh=hnWLqYXx/enUl3blN9H38oqkLIXAr0tyRzvlFpRYzeI=; b=f4kUoD1+wFCRZCKzz9ts28rLLmSjLLQmYv3IwTvoN71eI0AtVgtGsrJfBSloaHEStA DRPxlfkrm5T5Y3dFl6RVk/p7ufxJx+j1C1i+YDhmcTnpghPD8wVo5HaPinIZ7uKTEEEe Bt/+rx7giPBMhHkW10u1WRvBLMCyOicN2vyz/Tv97HjFqdDn9YU9EvkXpu/zHL9o1AWf cVsneQfIEebzN1EBItHg97wtPQsz2avNQYIWnuLdbdVeUjw69J3wYP34NYXYYj7yQjip ZRSML3llF+o+KwT2wBpWqn60D3Y5mz3ReA/wPx3grW0+FbgndtXoLbYOq34OuxaHIjXJ L49A==; dara=google.com",
    "arc-authentication-results": "i=1; mx.google.com; dkim=pass header.i=@getsentry.com header.s=m1 header.b=ffeVbqoi; dkim=pass header.i=@sendgrid.info header.s=smtpapi header.b=uH7uDCR0; spf=pass (google.com: domain of bounces+2307627-93ed-liencf=gmail.com@md.getsentry.com designates 167.89.84.75 as permitted sender) smtp.mailfrom=\"bounces+2307627-93ed-liencf=gmail.com@md.getsentry.com\"; dmarc=pass (p=REJECT sp=REJECT dis=NONE) header.from=md.getsentry.com",
    "return-path": [
      {
        "address": "bounces+2307627-93ed-liencf=gmail.com@md.getsentry.com",
        "name": ""
      }
    ],
    "received-spf": "pass (google.com: domain of bounces+2307627-93ed-liencf=gmail.com@md.getsentry.com designates 167.89.84.75 as permitted sender) client-ip=167.89.84.75;",
    "authentication-results": "mx.google.com; dkim=pass header.i=@getsentry.com header.s=m1 header.b=ffeVbqoi; dkim=pass header.i=@sendgrid.info header.s=smtpapi header.b=uH7uDCR0; spf=pass (google.com: domain of bounces+2307627-93ed-liencf=gmail.com@md.getsentry.com designates 167.89.84.75 as permitted sender) smtp.mailfrom=\"bounces+2307627-93ed-liencf=gmail.com@md.getsentry.com\"; dmarc=pass (p=REJECT sp=REJECT dis=NONE) header.from=md.getsentry.com",
    "dkim-signature": "[object Object],[object Object]",
    "content-type": "multipart/alternative",
    "mime-version": "1.0",
    "subject": "Weekly Report for Xamide: November 8th, 2025 - November 15th, 2025",
    "from": [
      {
        "address": "noreply@md.getsentry.com",
        "name": "Sentry"
      }
    ],
    "date": "Sun Nov 16 2025 02:38:54 GMT+0800 (台北標準時間)",
    "message-id": "<20251115183853.608487.19199@md.getsentry.com>",
    "x-sg-eid": "=?us-ascii?Q?u001=2EsDAWlfbXXGupROvum8uzjYcMZKVuuGbL=2Fank7dazu0rv+KCUrXlIMNCGS?= =?us-ascii?Q?DEZFSq2Cj0upQJwXkoZ4OH517+5ZfENm0ixKZaQ?= =?us-ascii?Q?HgHuw+cnRhOOMN5f=2FHsPXGvsGJAfuwlKSt3zAze?= =?us-ascii?Q?=2FGFHHA4o5nv9eB1NUzGLnmRyZIRHtwumOT12ZoQ?= =?us-ascii?Q?xgH9Wsd3f0l9kGo++S8VzBIHl3KeMYYcHWC2JAO?= =?us-ascii?Q?QxaRGmQwT=2Fh0dfpxE4X+H4=3D?=",
    "x-sg-id": "=?us-ascii?Q?u001=2ESdBcvi+Evd=2FbQef8eZF3BhJqhvxwQRRneMX1tlS=2Fn4ASTP4fzXZahrSu8?= =?us-ascii?Q?dzNhNlGSSmFVSHlTCK2auDf5KBwFL72jzF4f=2FRK?= =?us-ascii?Q?eKDChSIkpIU=3D?=",
    "to": [
      {
        "address": "liencf@gmail.com",
        "name": ""
      }
    ],
    "x-entity-id": "u001.qFBnU0fmuUhhSftCrEUw1Q=="
  },
  "attachments": []
}