{
  "index": 678,
  "fromLine": "From service@pxbillrc01.cathaybk.com.tw Wed Oct 29 06:18:32 2025",
  "subject": "國泰世華銀行信用卡繳款入帳彙整通知",
  "from": "\"國泰世華銀行\" <service@pxbillrc01.cathaybk.com.tw>",
  "to": "\"連志峰\" <liencf@gmail.com>",
  "date": "2025-10-29T04:18:06.000Z",
  "messageId": "<ba4597d88e7875e8@a81abd05510826d6>",
  "topContentType": "[object Object]",
  "mime": {
    "hasText": false,
    "hasHtml": true,
    "attachmentCount": 1
  },
  "headers": {
    "delivered-to": [
      {
        "address": "liencf@gmail.com",
        "name": ""
      }
    ],
    "received": "by 2002:a05:7010:d209:b0:4d4:9739:2b92 with SMTP id ji9csp2426752mdb; Tue, 28 Oct 2025 23:18:32 -0700 (PDT),from pxbillsd04.cathaybk.com.tw (pxbillsd04.cathaybk.com.tw. [60.251.89.222]) by mx.google.com with ESMTPS id 41be03b00d2f7-b71f5536743si6148416a12.1182.2025.10.28.23.17.59 for <liencf@gmail.com> (version=TLS1_2 cipher=ECDHE-ECDSA-AES128-GCM-SHA256 bits=128/128); Tue, 28 Oct 2025 23:18:32 -0700 (PDT)",
    "x-google-smtp-source": "AGHT+IHGN5ZXqazOx7VpeGkmsYBKyO+dyS5jqRS/KMbSqjUUddAauCJbDPJrsiNBOKqTXG4nmxVF",
    "x-received": "by 2002:a05:6a21:99a8:b0:342:b918:b475 with SMTP id adf61e73a8af0-3465194f029mr2231803637.21.1761718712293; Tue, 28 Oct 2025 23:18:32 -0700 (PDT)",
    "arc-seal": "i=1; a=rsa-sha256; t=1761718712; cv=none; d=google.com; s=arc-20240605; b=HPxBLe0msKQwK9Vh928XP4bmCLhav0+STiJOOjMxOZ0JE2ryaXGCZovM7hPpMllTam h0v9m1hkKEXSDupKSNxMl7Idjz8mE7IK4GJjKABfONZ5GY55LKrJ0pUaNB6w5nc2m5eQ XrRgS90lchSrU29WLCIIXZWOFjHGE09egmvXOtQmsCy9e42Xn9Kw5jyeqadAJo4fHsbw VDKc6/HhZh72uSUlVMmqf0CuuQdJUlP7V3XNyJJklzOJiQaa960isM4HGQ31xFi53J/Z ku7eGFbjUL+36am7vq5Hl3OsL9ZyfQKvIgHxg7Fpx/Mvt977Knmu1CIEDUjZl6092WOP mD/A==",
    "arc-message-signature": "i=1; a=rsa-sha256; c=relaxed/relaxed; d=google.com; s=arc-20240605; h=content-transfer-encoding:thread-index:precedence:subject:reply-to :to:from:date:message-id:mime-version:dkim-signature; bh=cFCDiu7C3Tj9eZADVQeF0pEN01Kbhc7bevtxlAx6bPM=; fh=KUG9u+JkIZ/6LNNAxu5VUstgOa2JrvMFVjux87MGpD0=; b=Nwf4gFjYMThHAt1SlQ61+3CGWCLm6Un0CJPXFspJAbK3U0me6xOKxaxVIKtBn+AyHY X7xTnQTxBOvzuGIMXHCXMMRKXuWcICkK+tPoagqQ5oW0vk0/DABdRVHYisObLMx2kPzt JZX0CGHCh0atY9ad1BIOhzB3rux9/2+W+vlc4TqJ400G80Dss6YQvHsQtz9luPp5yhfm s3AVD8he4h1ufqv+5mx8uLubIsxSHoZPJuGhD0yWfIiXH/DSO04jKDz2TFLee7hRCqHc wgN1UT6tjQ8BU+UT5MUCWTHEITrGgwrrjnz0nIdzLswj59Cq8n2mL9zhakQIUH2grhK4 cRjw==; dara=google.com",
    "arc-authentication-results": "i=1; mx.google.com; dkim=pass header.i=@cathaybk.com.tw header.s=rcn header.b=yMgEgbWx; spf=pass (google.com: domain of service@pxbillrc01.cathaybk.com.tw designates 60.251.89.222 as permitted sender) smtp.mailfrom=service@pxbillrc01.cathaybk.com.tw; dmarc=pass (p=NONE sp=NONE dis=NONE) header.from=cathaybk.com.tw",
    "return-path": [
      {
        "address": "service@pxbillrc01.cathaybk.com.tw",
        "name": ""
      }
    ],
    "received-spf": "pass (google.com: domain of service@pxbillrc01.cathaybk.com.tw designates 60.251.89.222 as permitted sender) client-ip=60.251.89.222;",
    "authentication-results": "mx.google.com; dkim=pass header.i=@cathaybk.com.tw header.s=rcn header.b=yMgEgbWx; spf=pass (google.com: domain of service@pxbillrc01.cathaybk.com.tw designates 60.251.89.222 as permitted sender) smtp.mailfrom=service@pxbillrc01.cathaybk.com.tw; dmarc=pass (p=NONE sp=NONE dis=NONE) header.from=cathaybk.com.tw",
    "dkim-signature": "v=1",
    "mime-version": "1.0",
    "message-id": "<ba4597d88e7875e8@a81abd05510826d6>",
    "date": "Wed Oct 29 2025 12:18:06 GMT+0800 (台北標準時間)",
    "from": [
      {
        "address": "service@pxbillrc01.cathaybk.com.tw",
        "name": "國泰世華銀行"
      }
    ],
    "to": [
      {
        "address": "liencf@gmail.com",
        "name": "連志峰"
      }
    ],
    "reply-to": [
      {
        "address": "service@cathaybk.com.tw",
        "name": ""
      }
    ],
    "subject": "國泰世華銀行信用卡繳款入帳彙整通知",
    "x-assurancesys-bulkmail": "1",
    "precedence": "bulk",
    "thread-index": "NzUxNzcxXzMyMzE4NTkyNg==",
    "content-type": "multipart/signed",
    "content-transfer-encoding": "7bit"
  },
  "attachments": [
    {
      "filename": "smime.p7s",
      "contentType": "application/x-pkcs7-signature",
      "size": 4693,
      "cid": "",
      "checksum": "1ea7378f481c272b3e3915c2b9ec5553"
    }
  ]
}