{
  "index": 271,
  "fromLine": "From security@mail.instagram.com Sun Nov 09 20:10:01 2025",
  "subject": "重設密碼",
  "from": "\"Instagram\" <security@mail.instagram.com>",
  "to": "liencf@gmail.com",
  "date": "2025-11-09T20:09:46.000Z",
  "messageId": "<a939befb-a5d5-4025-a48f-361fc4a00986@mail.instagram.com>",
  "topContentType": "[object Object]",
  "mime": {
    "hasText": true,
    "hasHtml": true,
    "attachmentCount": 0
  },
  "headers": {
    "delivered-to": [
      {
        "address": "liencf@gmail.com",
        "name": ""
      }
    ],
    "received": "by 2002:a05:7011:1e11:b0:4ec:1446:8385 with SMTP id uy17csp776631mdb; Sun, 9 Nov 2025 12:10:02 -0800 (PST),from 69-171-232-144.mail-mail.facebook.com (69-171-232-144.mail-mail.facebook.com. [69.171.232.144]) by mx.google.com with ESMTPS id 586e51a60fabf-3e41f13a68bsi4944571fac.136.2025.11.09.12.10.01 for <liencf@gmail.com> (version=TLS1_3 cipher=TLS_AES_256_GCM_SHA384 bits=256/256); Sun, 09 Nov 2025 12:10:01 -0800 (PST)",
    "x-google-smtp-source": "AGHT+IECKGVCyUdTLZe5PEtzn/hbJSoM1cQ9btDnU8FwWxUEg43+wjBtV3B+TrebGN6tl6gWxfP8",
    "x-received": "by 2002:a05:6870:d415:b0:343:a20a:3fd5 with SMTP id 586e51a60fabf-3e7c2857267mr4141593fac.40.1762719001886; Sun, 09 Nov 2025 12:10:01 -0800 (PST)",
    "arc-seal": "i=1; a=rsa-sha256; t=1762719001; cv=none; d=google.com; s=arc-20240605; b=ZySgYk3llhKBembV1SUfzUMiFC3PdO4Yw9i3r/linBqWI9bWcv0sZwXaVPExUowHP5 28PNTu67TJlFTS8oPlfbQmt4UpFiZUcfbI1evIUQQl/pBjcWR+VELvFiDL7M2YkMJxTy yfdW/fnwuK+g6caDiLdrqPFmtrfnrtgiF0KwP+JGabUyWS8AmXrvDSz6dF2ppUdy3yRB lUhMboAu0/lQad3xRLvY0hrnLkKepoFJ9438jP2bWf68HDE4b4ZL4gA6oEIHQWk9zUnB A534z5tzl0gNTGAhU8ddTvIqG1hO6SfX/DFr3+ULrcg1FQkzF5++iHUKFjIgnN6bBHOB 64Xw==",
    "arc-message-signature": "i=1; a=rsa-sha256; c=relaxed/relaxed; d=google.com; s=arc-20240605; h=message-id:content-transfer-encoding:mime-version:feedback-id :bimi-selector:list-unsubscribe:errors-to:reply-to:from:subject:to :date:dkim-signature; bh=zuPjYw+X13fy1d+2yDu26PaVcKXDtVfRVuUlglFH5uU=; fh=hnWLqYXx/enUl3blN9H38oqkLIXAr0tyRzvlFpRYzeI=; b=QFceUKddmAIbSQ5VGdpys7B36Z1zOk7PSp5c0l1GnDd8ASAkx2b1Wtu7r6YWklFcr/ zMWqpHXJ3tJRNEBFu/R6bBmAgFb/eVX1RU1BBB9zeq4Q9/1EVontQhTvNkbI8liL7Fzb Eh0ZqKgDtm10ZqiXdrsldPFUBdVb3ezfXcr0Ze2Z1xpywHxaDcIbPo03xdV6e2PWvgSp rsWE7dhZuiTFx7vgr7aZ2Hs5yG+ANChOqyaOpl9w5qm3DNLA4M7dYeWXYLPnG8Am0beC vV2Wcx0Fq/9a39tVbGce0aBRjJuawC0xJ3XMwBYmm8OCQpr8NxpZ5inpPEB858NUhvaL Nv8w==; dara=google.com",
    "arc-authentication-results": "i=1; mx.google.com; dkim=pass header.i=@mail.instagram.com header.s=s1024-2013-q3 header.b=LADx2YtD; spf=pass (google.com: domain of security@mail.instagram.com designates 69.171.232.144 as permitted sender) smtp.mailfrom=security@mail.instagram.com; dmarc=pass (p=REJECT sp=REJECT dis=NONE) header.from=mail.instagram.com",
    "return-path": "[object Object],[object Object]",
    "received-spf": "pass (google.com: domain of security@mail.instagram.com designates 69.171.232.144 as permitted sender) client-ip=69.171.232.144;",
    "authentication-results": "mx.google.com; dkim=pass header.i=@mail.instagram.com header.s=s1024-2013-q3 header.b=LADx2YtD; spf=pass (google.com: domain of security@mail.instagram.com designates 69.171.232.144 as permitted sender) smtp.mailfrom=security@mail.instagram.com; dmarc=pass (p=REJECT sp=REJECT dis=NONE) header.from=mail.instagram.com",
    "dkim-signature": "v=1",
    "x-facebook": "from 2803:6080:5850:519d:4957:e585:14ab:a00 ([MTI3LjAuMC4x])  by thrift.facebook.com with HTTPS (ZuckMail);",
    "date": "Mon Nov 10 2025 04:09:46 GMT+0800 (台北標準時間)",
    "to": [
      {
        "address": "liencf@gmail.com",
        "name": ""
      }
    ],
    "subject": "重設密碼",
    "priority": "normal",
    "x-mailer": "ZuckMail [version 1.00]",
    "from": [
      {
        "address": "security@mail.instagram.com",
        "name": "Instagram"
      }
    ],
    "reply-to": [
      {
        "address": "security@mail.instagram.com",
        "name": "Instagram"
      }
    ],
    "errors-to": "security@mail.instagram.com",
    "x-facebook-notify": "password_reset_optimized; mailid=U2U6432eb566b5a5G24bc2cdafc3378G6432efefcb877G5628",
    "list": "[object Object]",
    "x-fb-internal-notiftype": "password_reset_optimized",
    "bimi-selector": "v=BIMI1; s=fb2025q1v1;",
    "feedback-id": "password_reset_optimized:Facebook",
    "x-fb-internal-mid": "U2U6432eb566b5a5G24bc2cdafc3378G6432efefcb877G5628",
    "x-fb-internal-recipid": "127864",
    "x-facebook-priority": "0",
    "x-auto-response-suppress": "All",
    "mime-version": "1.0",
    "content-transfer-encoding": "quoted-printable",
    "content-type": "text/html",
    "message-id": "<a939befb-a5d5-4025-a48f-361fc4a00986@mail.instagram.com>"
  },
  "attachments": []
}