{
  "index": 1196,
  "fromLine": "From donotreply@zeczec.com Tue Oct 14 13:33:28 2025",
  "subject": "【在家吃生魚片｜生魚一刀】一把真正好用的家用魚刀／【Vermicular 小Ｖ 鑄鐵料理壺】是壺也是鍋，單手輕鬆煮／【ASMOT+ 整眠枕】來自日本的睡眠修復",
  "from": "\"嘖嘖 zeczec\" <donotreply@zeczec.com>",
  "to": "liencf@gmail.com",
  "date": "2025-10-14T13:07:16.000Z",
  "messageId": "<2ec2cc85d53a601d793684199.c8499353ab.20251014130705.9dcaebdee6.ccab93f3@mail196.atl101.mcdlv.net>",
  "topContentType": "[object Object]",
  "mime": {
    "hasText": true,
    "hasHtml": true,
    "attachmentCount": 0
  },
  "headers": {
    "delivered-to": [
      {
        "address": "liencf@gmail.com",
        "name": ""
      }
    ],
    "received": "by 2002:a05:7010:df93:b0:4ca:2b22:f54c with SMTP id ok19csp4571192mdb; Tue, 14 Oct 2025 06:33:29 -0700 (PDT),from mail196.atl101.mcdlv.net (mail196.atl101.mcdlv.net. [198.2.130.196]) by mx.google.com with ESMTPS id d75a77b69052e-4e70706246fsi56715861cf.602.2025.10.14.06.33.28 for <liencf@gmail.com> (version=TLS1_3 cipher=TLS_AES_256_GCM_SHA384 bits=256/256); Tue, 14 Oct 2025 06:33:28 -0700 (PDT),from localhost (localhost [127.0.0.1]) by mail196.atl101.mcdlv.net (Mailchimp) with ESMTP id 4cmFFw66ZwzHbC0v5 for <liencf@gmail.com>; Tue, 14 Oct 2025 13:20:36 +0000 (GMT)",
    "x-google-smtp-source": "AGHT+IF/cFkw3rK4/OCNF9T2VljniOBv0VPj1vPt4KozeT38wIAUp+Tl7Yn0NbnZifTOO5IPUxGG",
    "x-received": "by 2002:a05:6214:2b06:b0:87a:9fe:1388 with SMTP id 6a1803df08f44-87b2efe8322mr316334056d6.55.1760448808849; Tue, 14 Oct 2025 06:33:28 -0700 (PDT)",
    "arc-seal": "i=1; a=rsa-sha256; t=1760448808; cv=none; d=google.com; s=arc-20240605; b=jWlexEl6FUr3eMn0O+kuMCi1sq//0rXeqboLR4K7PhzJ1rp3nysc/Ge1aG41nLkPzh 2PIQTS0Cl5oAyNdQ3oTuIGGXrHj7N2E8E4XAtNivMowhCHQ+sNEdt/cuJTHiAl7YpR6M 1ECvdeh7gqWWN5Nx2BkBC0V6pVt/r97hpLmyd9Gp1QgLl5qG55R/6zY3pAa8PHp8/Vqo sZiAtLrx6Rn1dBHwpWMTIqLA6tbkHMiVA3ABF/C+QVbRqmTItOTuqHOLxbDkcHMI0VnE Y7PAanjbsk6x0/geNQOKCEeLqbFEAbTe80N4ThtKIvv4PZxefiipJpVHNGl2j3VNIoLB srjA==",
    "arc-message-signature": "i=1; a=rsa-sha256; c=relaxed/relaxed; d=google.com; s=arc-20240605; h=mime-version:list-unsubscribe-post:list-unsubscribe:list-id :feedback-id:message-id:date:to:reply-to:from:subject:dkim-signature :dkim-signature; bh=hV6YIxzKr26YnWbTHUpCpgrRHjpVQFWGsxbZBo5LTk0=; fh=AuRPPJxWT3oDWns/IAyV12DuHusfebFT2kEqOaRmmSo=; b=cKhwM+QXfE448EnqM6v5vgTJ8fqIanIimrAm+9U+RslkPJMBnamu4kEsYnZH9Y9YE+ kPBQtYVFIddUgBe31IUvCd1LYfJ13D5sZYddvMgrfTIdyW9IdgvPTtCqRy7nNdNrdus6 +xyYOdsDLnyOfbNeP8vbBW+prn/24aP/yGe8FsLKqYnK6EZlMJyMVbIsafPROckJ8prQ Na0VDaeQo/pjbz9didkJ2NusW1SkQ42M/P009VqDyJ9hnT3fvx1LLB8TlyHtkQPMohhV 9XQgnuFXyt60PGPFw/LZQs4f09o+x96CI75q8o6Rcm57EAtS6No7OId5ozMVYUR6UrB9 bXTw==; dara=google.com",
    "arc-authentication-results": "i=1; mx.google.com; dkim=pass header.i=@gmail.mcsv.net header.s=k2 header.b=bEB7Tpnm; dkim=pass header.i=@zeczec.com header.s=k1 header.b=Eef+SVTN; spf=pass (google.com: domain of bounce-mc.us4_8610549.10079882-c8499353ab@mail196.atl101.mcdlv.net designates 198.2.130.196 as permitted sender) smtp.mailfrom=bounce-mc.us4_8610549.10079882-c8499353ab@mail196.atl101.mcdlv.net; dmarc=pass (p=NONE sp=NONE dis=NONE) header.from=zeczec.com",
    "return-path": [
      {
        "address": "bounce-mc.us4_8610549.10079882-c8499353ab@mail196.atl101.mcdlv.net",
        "name": ""
      }
    ],
    "received-spf": "pass (google.com: domain of bounce-mc.us4_8610549.10079882-c8499353ab@mail196.atl101.mcdlv.net designates 198.2.130.196 as permitted sender) client-ip=198.2.130.196;",
    "authentication-results": "mx.google.com; dkim=pass header.i=@gmail.mcsv.net header.s=k2 header.b=bEB7Tpnm; dkim=pass header.i=@zeczec.com header.s=k1 header.b=Eef+SVTN; spf=pass (google.com: domain of bounce-mc.us4_8610549.10079882-c8499353ab@mail196.atl101.mcdlv.net designates 198.2.130.196 as permitted sender) smtp.mailfrom=bounce-mc.us4_8610549.10079882-c8499353ab@mail196.atl101.mcdlv.net; dmarc=pass (p=NONE sp=NONE dis=NONE) header.from=zeczec.com",
    "dkim-signature": "[object Object],[object Object]",
    "subject": "【在家吃生魚片｜生魚一刀】一把真正好用的家用魚刀／【Vermicular 小Ｖ 鑄鐵料理壺】是壺也是鍋，單手輕鬆煮／【ASMOT+ 整眠枕】來自日本的睡眠修復",
    "from": [
      {
        "address": "donotreply@zeczec.com",
        "name": "嘖嘖 zeczec"
      }
    ],
    "reply-to": [
      {
        "address": "donotreply@zeczec.com",
        "name": "嘖嘖 zeczec"
      }
    ],
    "to": [
      {
        "address": "liencf@gmail.com",
        "name": ""
      }
    ],
    "date": "Tue Oct 14 2025 21:07:16 GMT+0800 (台北標準時間)",
    "message-id": "<2ec2cc85d53a601d793684199.c8499353ab.20251014130705.9dcaebdee6.ccab93f3@mail196.atl101.mcdlv.net>",
    "x-mailer": "Mailchimp Mailer - **CID9dcaebdee6c8499353ab**",
    "x-campaign": "mailchimp2ec2cc85d53a601d793684199.9dcaebdee6",
    "x-campaignid": "mailchimp2ec2cc85d53a601d793684199.9dcaebdee6",
    "x-report-abuse": "Please report abuse for this campaign here: https://mailchimp.com/contact/abuse/?u=2ec2cc85d53a601d793684199&id=9dcaebdee6&e=c8499353ab",
    "x-mc-user": "2ec2cc85d53a601d793684199",
    "feedback-id": "8610549:8610549.10079882:us4:mc",
    "list": "[object Object]",
    "x-accounttype": "pd",
    "content-type": "multipart/alternative",
    "mime-version": "1.0"
  },
  "attachments": []
}